Metadata-Version: 2.1
Name: rmspace
Version: 5
Summary: Remove trailing whitespace from code and other plain-text files.
Home-page: UNKNOWN
Author: Olle Lindgren
Author-email: lindgrenolle@live.se
License: UNKNOWN
Platform: UNKNOWN
License-File: LICENSE
